Metadata-Version: 2.1
Name: pytest-factoryboy-fixtures
Version: 0.1
Summary: Generates pytest fixtures that allow the use of type hinting
Home-page: https://github.com/G-HenriquezV/pytest-factoryboy-fixtures
Author: Germán Henríquez
Author-email: germanandres.hv@gmail.com
License: UNKNOWN
Platform: UNKNOWN
Classifier: Programming Language :: Python :: 3
Classifier: License :: OSI Approved :: MIT License
Classifier: Operating System :: OS Independent
Classifier: License :: OSI Approved :: MIT License
Requires-Python: >=3.6
